MANIFEST.in
README.rst
setup.py
pineapple/__init__.py
pineapple/magic.py
pineapple/require.py
pineapple/runtest.py
pineapple.egg-info/PKG-INFO
pineapple.egg-info/SOURCES.txt
pineapple.egg-info/dependency_links.txt
pineapple.egg-info/not-zip-safe
pineapple.egg-info/pbr.json
pineapple.egg-info/requires.txt
pineapple.egg-info/top_level.txt