Metadata-Version: 1.1
Name: pineapple
Version: 0.4
Summary: Utility functions for the Pineapple IPython/Jupyter front-end
Home-page: https://github.com/nwhitehead/pineapple-module/
Author: Nathan Whitehead
Author-email: nwhitehe@gmail.com
License: ISC
Keywords: Pineapple,IPython,Jupyter,reproducible,versions,package,modules
Platform: UNKNOWN
Classifier: Development Status :: 3 - Alpha
Classifier: License :: OSI Approved :: ISC License (ISCL)
Classifier: Programming Language :: Python :: 2.7
Classifier: Framework :: IPython
Classifier: Topic :: Software Development :: Libraries :: Python Modules
